langframe_cloud/__init__.py
langframe_cloud/auth_client/__init__.py
langframe_cloud/auth_client/client.py
langframe_cloud/hasura_client/__init__.py
langframe_cloud/hasura_client/client.py
langframe_cloud/hasura_client/hasura_execution.py
langframe_cloud/hasura_client/custom_base_client/async_base_client.py
langframe_cloud/hasura_client/generated_graphql_client/__init__.py
langframe_cloud/hasura_client/generated_graphql_client/async_base_client.py
langframe_cloud/hasura_client/generated_graphql_client/base_model.py
langframe_cloud/hasura_client/generated_graphql_client/client.py
langframe_cloud/hasura_client/generated_graphql_client/create_app.py
langframe_cloud/hasura_client/generated_graphql_client/create_ephemeral_catalog.py
langframe_cloud/hasura_client/generated_graphql_client/create_execution_session_for_app.py
langframe_cloud/hasura_client/generated_graphql_client/create_namespace.py
langframe_cloud/hasura_client/generated_graphql_client/create_namespace_with_properties.py
langframe_cloud/hasura_client/generated_graphql_client/create_query_execution.py
langframe_cloud/hasura_client/generated_graphql_client/create_standard_catalog.py
langframe_cloud/hasura_client/generated_graphql_client/create_table.py
langframe_cloud/hasura_client/generated_graphql_client/create_table_with_properties.py
langframe_cloud/hasura_client/generated_graphql_client/create_user.py
langframe_cloud/hasura_client/generated_graphql_client/create_view.py
langframe_cloud/hasura_client/generated_graphql_client/create_view_with_properties.py
langframe_cloud/hasura_client/generated_graphql_client/dataset_exists.py
langframe_cloud/hasura_client/generated_graphql_client/delete_namespace_properties.py
langframe_cloud/hasura_client/generated_graphql_client/drop_dataset.py
langframe_cloud/hasura_client/generated_graphql_client/drop_namespace.py
langframe_cloud/hasura_client/generated_graphql_client/enums.py
langframe_cloud/hasura_client/generated_graphql_client/exceptions.py
langframe_cloud-0.1.2.dist-info/METADATA
langframe_cloud-0.1.2.dist-info/WHEEL
langframe_cloud-0.1.2.dist-info/licenses/LICENSE
langframe_cloud-0.1.2.dist-info/RECORD
