Metadata-Version: 2.4
Name: langframe-cloud
Version: 0.1.2
Summary: Collection of utilities to allow langframe OSS to communicate with typedef cloud.
Author-email: typedef <hello@typedef.ai>
License-Expression: LicenseRef-Proprietary
License-File: LICENSE
Classifier: License :: Other/Proprietary License
Classifier: Operating System :: OS Independent
Classifier: Programming Language :: Python :: 3
Requires-Python: >=3.10
Requires-Dist: grpcio>=1.60.0
Requires-Dist: httpx~=0.23
Requires-Dist: protobuf>=4.25.1
Requires-Dist: pydantic<3.0.0,>=2.0.0
Requires-Dist: requests>=2.31.0
Requires-Dist: websockets~=11.0
